terminal_pagination/__init__.py
terminal_pagination/input.py
terminal_pagination/terminal_pagination.py
terminal_pagination/underline.py
terminal_pagination-0.0.5.dist-info/LICENSE.txt
terminal_pagination-0.0.5.dist-info/METADATA
terminal_pagination-0.0.5.dist-info/WHEEL
terminal_pagination-0.0.5.dist-info/top_level.txt
terminal_pagination-0.0.5.dist-info/RECORD
